__init__.py
elody/__init__.py
elody/client.py
elody/csv.py
elody/error_codes.py
elody/exceptions.py
elody/job.py
elody/loader.py
elody/schemas.py
elody/util.py
elody/validator.py
elody/migration/__init__.py
elody/migration/base_object_migrator.py
elody/object_configurations/__init__.py
elody/object_configurations/base_object_configuration.py
elody/object_configurations/elody_configuration.py
elody/object_configurations/job_configuration.py
elody/object_configurations/saved_search_configuration.py
elody/policies/__init__.py
elody/policies/helpers.py
elody/policies/permission_handler.py
elody/policies/authentication/__init__.py
elody/policies/authentication/base_user_tenant_validation_policy.py
elody/policies/authentication/multi_tenant_policy.py
elody/policies/authentication/x_user_headers_policy.py
elody/policies/authorization/__init__.py
elody/policies/authorization/filter_generic_objects_policy.py
elody/policies/authorization/filter_generic_objects_policy_v2.py
elody/policies/authorization/generic_object_detail_policy.py
elody/policies/authorization/generic_object_mediafiles_policy.py
elody/policies/authorization/generic_object_metadata_policy.py
elody/policies/authorization/generic_object_relations_policy.py
elody/policies/authorization/generic_object_request_policy.py
elody/policies/authorization/generic_object_request_policy_v2.py
elody/policies/authorization/mediafile_derivatives_policy.py
elody/policies/authorization/mediafile_download_policy.py
elody/policies/authorization/multi_tenant_policy.py
elody/policies/authorization/tenant_request_policy.py
elody-0.0.232.dist-info/licenses/LICENSE
tests/__init_.py
tests/data.py
tests/unit/__init__.py
tests/unit/test_csv.py
tests/unit/test_utils.py
elody-0.0.232.dist-info/METADATA
elody-0.0.232.dist-info/WHEEL
elody-0.0.232.dist-info/top_level.txt
elody-0.0.232.dist-info/RECORD
