Metadata-Version: 2.4
Name: elody
Version: 0.0.232
Summary: elody SDK for Python
Author-email: Inuits <developers@inuits.eu>
License:                     GNU GENERAL PUBLIC LICENSE
Project-URL: Homepage, https://github.com/inuits/elody-python-sdk
Keywords: elody,SDK
Classifier: License :: OSI Approved :: GNU General Public License v2 (GPLv2)
Classifier: Intended Audience :: Developers
Classifier: Programming Language :: Python :: 3
Classifier: Programming Language :: Python :: 3.8
Classifier: Programming Language :: Python :: 3.9
Classifier: Programming Language :: Python :: 3.10
Classifier: Programming Language :: Python :: 3.11
License-File: LICENSE
Requires-Dist: certifi>=2023.5.7
Requires-Dist: charset-normalizer>=3.2.0
Requires-Dist: idna>=3.4
Requires-Dist: requests>=2.31.0
Requires-Dist: urllib3>=1.26.16
Provides-Extra: loader
Requires-Dist: APScheduler>=3.10.4; extra == "loader"
Requires-Dist: cloudevents>=1.9.0; extra == "loader"
Requires-Dist: inuits-policy-based-auth>=10.0.1; extra == "loader"
Requires-Dist: jsonschema>=4.23.0; extra == "loader"
Requires-Dist: pytz>=2024.1; extra == "loader"
Requires-Dist: six>=1.16.0; extra == "loader"
Requires-Dist: tzlocal>=5.2; extra == "loader"
Provides-Extra: util
Requires-Dist: cloudevents>=1.9.0; extra == "util"
Dynamic: license-file
